gb_distributions_rjv
