Metadata-Version: 1.2
Name: gb-distributions-rjv
Version: 0.2
Summary: Gaussian distributions
Home-page: UNKNOWN
Author: Rajeev
Author-email: rjv.kumar18@gmail.com
License: UNKNOWN
Platform: UNKNOWN
Classifier: Programming Language :: Python :: 3
Classifier: License :: OSI Approved :: MIT License
Classifier: Operating System :: OS Independent
Requires-Python: >=3.*
